MemorySubSystemForCPU/DataMemory/alumod.v

module FORWARD(DATA2,Result);  //Module to forward the data to the output  
input [7:0] DATA2;             //Declaration of 8 bit input port
output  [7:0] Result;           //Declarartion of one 8 bit output port

assign #1 Result=DATA2;  //Data2 is assigned to the output port after a time delay of 1 time unit

endmodule


module ADD(DATA1,DATA2,Result); //Module to add data

input [7:0] DATA1,DATA2;        //Declaration of two 8 bit input ports
output [7:0] Result;            //Declarartion of one 8 bit output port



  assign #2 Result= DATA1 + DATA2;
                           //After a time delay of 2 time units Data1 and Data2 is added and assigned to result

endmodule


module AND(DATA1,DATA2,Result); //Module for the AND operation

input [7:0] DATA1,DATA2;        //Declaration of two 8 bit input ports
output [7:0] Result;            //Declarartion of one 8 bit output port


  assign #1 Result= DATA1 & DATA2;
                       //After a time delay of 1 time unit Data1 and Data2 are AND and then assigned to result

endmodule


module OR(DATA1,DATA2,Result); //Module for the OR operation
input [7:0] DATA1,DATA2;       //Declaration of two 8 bit input ports
output [7:0] Result;           //Declarartion of one 8 bit output port


  assign #1 Result=DATA1 | DATA2;
                          //After a time delay of 1 time unit Data1 and Data2 goes through  OR operation and assigned to the result



endmodule



module alu(DATA1, DATA2, RESULT, SELECT,ZERO); //Main module for the ALU

input [7:0] DATA1,DATA2;                  //Declaration of two 8 bit input ports
input [2:0] SELECT;                       //Declarartion of one 2 bit output port port
output reg [7:0] RESULT;	          //Declarartion of one 8 bit output port register	
output reg ZERO;                 	//Declarartion of one bit output port register	
wire [7:0] WFORWARD,WADD,WAND,WOR;      //Declarartion of four 8 bit wires



FORWARD F1 (DATA2,WFORWARD);        //instantiating FORWARD module as F1
ADD F2 (DATA1, DATA2,WADD);        //instantiating ADD module as F2
AND F3 (DATA1, DATA2,WAND);        //instantiating AND module as F3
OR F4 (DATA1, DATA2,WOR);         //instantiating OR modue as F4

always@(SELECT,WFORWARD,WADD,WAND,WOR) //always block is executed when either one of the sesitivity list is triggered
begin
case(SELECT)                          

3'b000:  RESULT=WFORWARD;      //When select is 000 output of FORWARD to result
3'b001:  RESULT=WADD;          //When select is 001 output of ADD to result
3'b010:  RESULT=WAND;          //When select is 010 output of AND to result
3'b011:  RESULT=WOR; 	       //When select is 011 output of OR to result

endcase

if(RESULT==8'b00000000)
ZERO=1'b1;
else
ZERO=1'b0;

end

endmodule

MemorySubSystemForCPU/DataMemory/regmod.v
module reg_file (IN, OUT1 , OUT2, INADDRESS, OUT1ADDRESS , OUT2ADDRESS , WRITE , CLK , RESET,BUSYWAIT); //Module for a REGISTER file

input [7:0] IN ;                                //8bit input port to get the input data
output [7:0] OUT1,OUT2;                         //2 8bit output ports to output the data
input  [2:0] INADDRESS,OUT1ADDRESS,OUT2ADDRESS ;//3 3bit input ports to input-address data
input WRITE,CLK,RESET;                          //3 input ports to get the write,clk and reset datas

reg [7:0] store [7:0] ;  
input BUSYWAIT;                       //8 8bit registers to store data

initial
begin
#5;
$display("\n\t\t\t---------------------------------------------------------------\n");
$display("\t\ttime\treg0\treg1\treg2\treg3\treg4\treg5\treg6\treg7\n");
$display("\n\t\t\t---------------------------------------------------------------\n");
$monitor($time, "\t%d\t%d\t%d\t%d\t%d\t%d\t%d\t%d",store[0],store[1],store[2],store[3],store[4],store[5],store[6],store[7]);
end


assign #2 OUT1= store[OUT1ADDRESS];   //after a time delay of two time units data in out1address register is read into the OUT1 port
assign #2 OUT2= store[OUT2ADDRESS];   //after a time delay of two time units data in out2address register is read into the OUT2 port

always @ (posedge  CLK ) //Always at a rising edge of  a clock the following code block is executed
 begin
 if (WRITE && !RESET && !BUSYWAIT)             //when write is enabaled
 	begin
	       #1 store[INADDRESS] = IN;  //fetch the data to the IN input and after a time delay of 1 time unit it is stored at the address of INADDRESS of the store register
	end
end


always @ (posedge  CLK ) //Always at a rising edge of  a clock the following code block is executed
 begin
if(RESET)           //if reset is enabled all the 8bit registers are set with zero
	begin 
	#1;
	      store[0]=    8'b00000000;
	      store[1]=    8'b00000000;
	      store[2]=    8'b00000000;
              store[3]=    8'b00000000;
	      store[4]=    8'b00000000;
	      store[5]=    8'b00000000;
	      store[6]=    8'b00000000;
	      store[7]=    8'b00000000;
	end
end
endmodule

MemorySubSystemForCPU/DataMemory/cpu.v
       /* 
	loadi   = "00000000";
	mov 	= "00000001";
	add 	= "00000010";
	sub 	= "00000011";
	and 	= "00000100";
	or 	= "00000101";
	j       = "00000110";
	beq	= "00000111";
	lwd 	= "00001000";
	lwi 	= "00001001";
	swd 	= "00001010";
	swi 	= "00001011";
*/


module cpu(PC, INSTRUCTION, CLK, RESET,BUSYWAIT,READ,WRITE,WRITEDATA,READDATA,ADDRESS);  //cpu main module with PC as output and INSTRUCTION CLK RESET as input

input [31:0] INSTRUCTION;                 //32bit input port to input the INSTRUCTION
input CLK,RESET;                          //2 input ports to input the CLK and RESET to the cpu
output reg [31:0] PC;                     //1 32bit output port register to store the program counter
output reg READ,WRITE;                    //output registers to store read and write signals
input BUSYWAIT;                           //input port  to input the busywait signals
input [7:0] READDATA;                     //8bit input port to store read data 
output reg [7:0] WRITEDATA;               //8bit output register to store the write data
output [7:0] ADDRESS;                     //8 bit output port to store the address
reg DatamemSelect;                        //register to store data memory select signals
reg WRITEENABLE;                          //register to store WRITEENABLE  signal
reg [7:0] INDATA;                         //8bit reg to store the in data
wire [7:0] aluresult,out1,out2;           //3 8bit wires to output the aluresult out1 and out2
reg select1,select2,select3,select4;      //4 registers to store the select signals
wire select5,and_output;                  //two wires to store intermediate outputs
reg  [2:0] ALUOP;                         //3 bit register to input the ALUOP selections to the alu
wire [7:0] complement;                    // 8 bit wire to output the complement 
reg  [7:0] outmux1,outmux2;              //2 8 bit registers to carry the intermediate outputs from the 1st and 2nd MUXs
reg  [31:0] pc;                          //32bit register to store the pc
wire ZERO;                               //A REGISTER TO STORE THE ALU OUTPUT SIGNAL OF THE BEQ INSTRUCTION


reg signed [9:0] leftshift;               //10 BIT SIGNED REGISTER TO STORE THE LEFT SHIFTED BINARY VALUE
reg signed [31:0] extended;               //32 BIT SIGNED REGISTER TO STORE THE SIGNED BINARY VALUE
wire  [31:0]target;                       //PC+4+OFFSET




always@(PC)
begin
#1 pc= pc+4;                             //pc is incremented by 4 bytes after a time interval of 1 time units
end

always@(posedge CLK)                    //always at the positive clock edge
begin
if(RESET)                               //when reset is enabled
begin
pc=0;                                   //pc is set to 0
#1 PC =  pc;                            //PC is also updated with 0 after a delay of 1 time unit
end
else
if(BUSYWAIT==0)
#1 PC =  pc;                            //else if BUSYWAIT is 0 PC is updated with the result in pc after a delay of 1 time unit
end




always@(INSTRUCTION)                   //always
begin
#1;
case(INSTRUCTION[31:24])  //first 8 bits of the INSTRUCTION is considered as the case

            
8'b00000010:begin //ADD selecter for add
	 ALUOP= 3'b001; 
         select1=0;
         select2=0;
	 select3=0;
	 select4=0;
	 WRITEENABLE=1;
	DatamemSelect=0;
	 READ=0;
	 WRITE=0;
         end
      
8'b00000011:begin//ADD selecter for sub
	ALUOP= 3'b001;
      	select1=1;
    	select2=0;
	select3=0;
	select4=0;
	WRITEENABLE=1;
	DatamemSelect=0;
	READ=0;
	WRITE=0;
	end                
8'b00000100:begin//AND selecter for and
	ALUOP= 3'b010;  
	select1=0;
        select2=0;
	select3=0;
	select4=0;
	WRITEENABLE=1;
	DatamemSelect=0;
	READ=0;
	WRITE=0;
	end      
8'b00000101:begin //OR selecter for or
	ALUOP= 3'b011;  
	select1=0;
	select2=0; 
	select3=0;
	select4=0;
	WRITEENABLE=1;
	DatamemSelect=0;
	 READ=0;
	 WRITE=0;
	end            
8'b00000001:begin//FORWARD selecter for mov
	ALUOP= 3'b000;
	select1=0;
	select2=0; 
	select3=0;
	select4=0;
	WRITEENABLE=1;
	DatamemSelect=0;
	READ=0;
	 WRITE=0;
	end  
            
8'b00000000:begin  //FORWARD selecter for loadi
	ALUOP= 3'b000;
	select1=0;
	select2=1;
	select3=0;
	select4=0;
	WRITEENABLE=1;
	DatamemSelect=0;
	READ=0;
	 WRITE=0;
	end
8'b00000111:begin  //ADD selecter for beq
	ALUOP= 3'b001;
	select1=1;
	select2=0;
	select3=1;
	select4=0;
	WRITEENABLE=0;
	DatamemSelect=0;
	READ=0;
	 WRITE=0;
	end       
8'b00000110:begin  // selecter for jump
	ALUOP= 3'b100;
	select1=0;
	select2=0;
	select3=0;
	select4=1;
	WRITEENABLE=0;
	DatamemSelect=0;
	READ=0;
	 WRITE=0;
	end  
8'b00001000:begin //selecter for lwd
        ALUOP= 3'b000;
	select1=0;
	select2=0;
	select3=0;
	select4=0;
	WRITEENABLE=1;
	DatamemSelect=1;
	READ=1;
	WRITE=0;
	end
     
8'b00001001:begin //selecter for lwi
        ALUOP= 3'b000;
	select1=0;
	select2=1;
	select3=0;
	select4=0;
	WRITEENABLE=1;
	DatamemSelect=1;
	READ=1;
	WRITE=0;
	end
8'b00001010:begin //selecter for swd
        ALUOP= 3'b000;
	select1=0;
	select2=0;
	select3=0;
	select4=0;
	WRITEENABLE=0;
	DatamemSelect=0;
	READ=0;
	WRITE=1;
	end
8'b00001011:begin //selecter for swi
        ALUOP= 3'b000;
	select1=0;
	select2=1;
	select3=0;
	select4=0;
        DatamemSelect=0;
	WRITEENABLE=0;
	READ=0;
	 WRITE=1;
	end
     
         
endcase
end


always@(negedge BUSYWAIT)           //at the negative edge of the busy wait signal read and write signals are set to zero
begin
READ=0;
WRITE=0;
end


always@(DatamemSelect,aluresult,READDATA)    
begin
if(DatamemSelect)                //if the data memory signal is high then INDATA is set with the READDATA
INDATA=READDATA;
else
INDATA=aluresult;                //else the INDATA is set with the alu result
end



reg_file myreg (INDATA, out1,out2,INSTRUCTION [18:16], INSTRUCTION[10:8] , INSTRUCTION[2:0] , WRITEENABLE , CLK , RESET,BUSYWAIT);
//aluresult as IN,out1,out2,WRITEREG as INSTRUCTION[18:16] ,OUT1ADDRESS as INSTRUCTION[10:8],OUT2ADDRESS as INSTRUCTION[2:0],WRITEENABLE,clk,reset


always@(out1,WRITEDATA)
begin
WRITEDATA=out1;            //always out1 is assigned to the write data register
end


assign #1 complement=(~out2+8'b00000001);   //complement=inverse+1(2's complement of operand 2)


always@(complement,out2,select1)       //always for mux1
begin
if (select1)       //if the instruction is SUB
     outmux1= complement;                //then send the complement as the output of outmux1
else
     outmux1=out2;                         //else send operand 2
end

always@(outmux1,INSTRUCTION,select2)               //always block for mux2
begin
if (select2)       //if the INSTRUCTION is loadi
     outmux2=INSTRUCTION[7:0];             //then output immediate value
else
    outmux2=outmux1;                       //else output operand 2
end

assign and_output=select3 & ZERO;       //ZERO SIGNAL AND SELECT3 SIGNALS ARE PASSED THROUGH AND OPERATION AND THE RESULT IS ASSIGNED IN THE AND_OUTPUT WIRE
assign select5=and_output |select4;    //AND_OUTPUT SIGNAL AND SELECT4 SIGNALS ARE PASSED THROUGH OR OPERATION AND THE RESULT IS ASSIGNED IN THE SELECT5 WIRE
 

always @(INSTRUCTION)
begin
leftshift[1:0]=2'b00;                //THE LEFT MOST TWO BITS ARE SET TO ZERO
leftshift[9:2]=INSTRUCTION[23:16];   //THE REMAINING 8 BITS ARE SET WITH THE REGISTER DESTINATION ADDRESS
extended[9:0]=leftshift[9:0];        //10 BITS OF THE LEFTSHIFT REGISTER IS MOVED TO THE RIGHTMOST 10 BITS OF EXTENDED REGISTER
extended[31:10]={22{leftshift[9]}};  //THE REMAINING LEFTMOST BITS OF THE EXTENDED REGISTER IS FILLED WITH THE SIGN BIT  OF THE LEFTSHIFT REG
end

assign #2 target=extended+PC+4;


always@(target,select5)               //always block for mux
begin
if (select5)       //if the INSTRUCTION is j,beq
     pc=target;    //THEN PC IS SET WITH THE FINAL OFFSET IN THE TARGET REGISTER            
else
    pc=PC+4;       //ELSE pc is updated with the next instruction
end



alu myalu (out1,outmux2,aluresult,ALUOP,ZERO);  //alu is instantiated as myalu
assign ADDRESS=aluresult;                       //assign the alu result to the address wire


endmodule

MemorySubSystemForCPU/DataMemory/dmem.v
 /*
Module  : 256x8-bit data memory 
Author  : Isuru Nawinne, Kisaru Liyanage
Date    : 25/05/2020

Description	:

This file presents a primitive data memory module for CO224 Lab 6 - Part 1
This memory allows data to be read and written as 1-Byte words
*/

module data_memory(
	clock,
    reset,
    read,
    write,
    address,
    writedata,
    readdata,
    busywait
);
input           clock;
input           reset;
input           read;
input           write;
input[7:0]      address;
input[7:0]      writedata;
output reg [7:0]readdata;
output reg      busywait;

//Declare memory array 256x8-bits 
reg [7:0] memory_array [255:0];

//Detecting an incoming memory access
reg readaccess, writeaccess;
always @(read, write)
begin
	busywait = (read || write)? 1 : 0;
	readaccess = (read && !write)? 1 : 0;
	writeaccess = (!read && write)? 1 : 0;
end

//Reading & writing
always @(posedge clock)
begin
    if(readaccess)
    begin
        readdata = #40 memory_array[address];
        busywait = 0;
		readaccess = 0;
    end
    if(writeaccess)
	begin
        memory_array[address] = #40 writedata;
        busywait = 0;
		writeaccess = 0;
    end
end

integer i;

//Reset memory
always @(posedge reset)
begin
    if (reset)
    begin
        for (i=0;i<256; i=i+1)
            memory_array[i] = 0;
        
        busywait = 0;
		readaccess = 0;
		writeaccess = 0;
    end
end

endmodule

MemorySubSystemForCPU/DataMemory/cpu_tb.v
// Computer Architecture (CO224) - Lab 05
// Design: Testbench of Integrated CPU of Simple Processor
// Author: Kisaru Liyanage

module cpu_tb;

    reg CLK, RESET;
    wire [31:0] PC;
    wire [31:0] INSTRUCTION;
    wire read,write,busywait;
    wire [7:0] address,readdata,writedata;
    
    /* 
    ------------------------
     SIMPLE INSTRUCTION MEM
    ------------------------
    */
    
    // TODO: Initialize an array of registers (8x1024) named 'instr_mem' to be used as instruction memory
    reg [7:0] instr_mem [1023:0];           //this is a vector of  1024 REGISTER of 8 bit width
    // TODO: Create combinational logic to support CPU instruction fetching, given the Program Counter(PC) value 
    //       (make sure you include the delay for instruction fetching here)
    assign #2 INSTRUCTION = {instr_mem[PC[9:0]+10'd3],instr_mem[PC[9:0]+10'd2],instr_mem[PC[9:0]+10'd1],instr_mem[PC[9:0]]}; //takes 32 bits for INSTRUCTION 
    



    initial
    begin
        // Initialize instruction memory with the set of instructions you need execute on CPU
        
        // METHOD 1: manually loading instructions to instr_mem
        // {instr_mem[10'd3], instr_mem[10'd2], instr_mem[10'd1], instr_mem[10'd0]} = 32'b00000000000001000000000000000101;
        // {instr_mem[10'd7], instr_mem[10'd6], instr_mem[10'd5], instr_mem[10'd4]} = 32'b00000000000000100000000000001001;
        // {instr_mem[10'd11], instr_mem[10'd10], instr_mem[10'd9], instr_mem[10'd8]} = 32'b00000010000001100000010000000010;
        
        // METHOD 2: loading instr_mem content from instr_mem.mem file
        $readmemb("./instr_mem.mem", instr_mem);
    end
    
    /* 
    -----
     CPU
    -----
    */





    data_memory my_data_memory(CLK,RESET,read,write,address,writedata,readdata,busywait);

    cpu mycpu(PC,INSTRUCTION, CLK,RESET,busywait,read,write,writedata,readdata,address);
             
    

   integer i;
    initial
    begin
    
        // generate files needed to plot the waveform using GTKWave
       $dumpfile("cpu_wavedata.vcd");
	$dumpvars(0, cpu_tb);
	for(i=0;i<8;i=i+1)$dumpvars(0, mycpu.myreg.store[i]);
        
        
        CLK = 1'b0;
        RESET = 1'b1;
        
        // TODO: Reset the CPU (by giving a pulse to RESET signal) to start the program execution
        #5 RESET=1'b0;
       
        // finish simulation after some time
        #500
        $finish;
        
    end
    
    // clock signal generation
    always
        #4 CLK = ~CLK;
        

endmodule

MemorySubSystemForCPU/DataMemory/cpu_wavedata.vcd
$date
	Fri Nov 13 15:33:48 2020
$end
$version
	Icarus Verilog
$end
$timescale
	1s
$end
$scope module cpu_tb $end
$var wire 8 ! writedata [7:0] $end
$var wire 1 " write $end
$var wire 8 # readdata [7:0] $end
$var wire 1 $ read $end
$var wire 1 % busywait $end
$var wire 8 & address [7:0] $end
$var wire 32 ' PC [31:0] $end
$var wire 32 ( INSTRUCTION [31:0] $end
$var reg 1 ) CLK $end
$var reg 1 * RESET $end
$var integer 32 + i [31:0] $end
$scope module my_data_memory $end
$var wire 1 ) clock $end
$var wire 1 * reset $end
$var wire 8 , writedata [7:0] $end
$var wire 1 " write $end
$var wire 1 $ read $end
$var wire 8 - address [7:0] $end
$var reg 1 % busywait $end
$var reg 1 . readaccess $end
$var reg 8 / readdata [7:0] $end
$var reg 1 0 writeaccess $end
$var integer 32 1 i [31:0] $end
$upscope $end
$scope module mycpu $end
$var wire 8 2 ADDRESS [7:0] $end
$var wire 1 % BUSYWAIT $end
$var wire 1 ) CLK $end
$var wire 32 3 INSTRUCTION [31:0] $end
$var wire 8 4 READDATA [7:0] $end
$var wire 1 * RESET $end
$var wire 1 5 and_output $end
$var wire 1 6 select5 $end
$var wire 32 7 target [31:0] $end
$var wire 8 8 out2 [7:0] $end
$var wire 8 9 out1 [7:0] $end
$var wire 8 : complement [7:0] $end
$var wire 8 ; aluresult [7:0] $end
$var wire 1 < ZERO $end
$var reg 3 = ALUOP [2:0] $end
$var reg 1 > DatamemSelect $end
$var reg 8 ? INDATA [7:0] $end
$var reg 32 @ PC [31:0] $end
$var reg 1 $ READ $end
$var reg 1 " WRITE $end
$var reg 8 A WRITEDATA [7:0] $end
$var reg 1 B WRITEENABLE $end
$var reg 32 C extended [31:0] $end
$var reg 10 D leftshift [9:0] $end
$var reg 8 E outmux1 [7:0] $end
$var reg 8 F outmux2 [7:0] $end
$var reg 32 G pc [31:0] $end
$var reg 1 H select1 $end
$var reg 1 I select2 $end
$var reg 1 J select3 $end
$var reg 1 K select4 $end
$scope module myalu $end
$var wire 8 L DATA2 [7:0] $end
$var wire 3 M SELECT [2:0] $end
$var wire 8 N WOR [7:0] $end
$var wire 8 O WFORWARD [7:0] $end
$var wire 8 P WAND [7:0] $end
$var wire 8 Q WADD [7:0] $end
$var wire 8 R DATA1 [7:0] $end
$var reg 8 S RESULT [7:0] $end
$var reg 1 < ZERO $end
$scope module F1 $end
$var wire 8 T DATA2 [7:0] $end
$var wire 8 U Result [7:0] $end
$upscope $end
$scope module F2 $end
$var wire 8 V DATA2 [7:0] $end
$var wire 8 W Result [7:0] $end
$var wire 8 X DATA1 [7:0] $end
$upscope $end
$scope module F3 $end
$var wire 8 Y DATA2 [7:0] $end
$var wire 8 Z Result [7:0] $end
$var wire 8 [ DATA1 [7:0] $end
$upscope $end
$scope module F4 $end
$var wire 8 \ DATA2 [7:0] $end
$var wire 8 ] Result [7:0] $end
$var wire 8 ^ DATA1 [7:0] $end
$upscope $end
$upscope $end
$scope module myreg $end
$var wire 1 % BUSYWAIT $end
$var wire 1 ) CLK $end
$var wire 8 _ IN [7:0] $end
$var wire 3 ` INADDRESS [2:0] $end
$var wire 8 a OUT1 [7:0] $end
$var wire 3 b OUT1ADDRESS [2:0] $end
$var wire 8 c OUT2 [7:0] $end
$var wire 3 d OUT2ADDRESS [2:0] $end
$var wire 1 * RESET $end
$var wire 1 B WRITE $end
$upscope $end
$upscope $end
$upscope $end
$scope module cpu_tb $end
$scope module mycpu $end
$scope module myreg $end
$var reg 8 e \store[0] [7:0] $end
$upscope $end
$upscope $end
$upscope $end
$scope module cpu_tb $end
$scope module mycpu $end
$scope module myreg $end
$var reg 8 f \store[1] [7:0] $end
$upscope $end
$upscope $end
$upscope $end
$scope module cpu_tb $end
$scope module mycpu $end
$scope module myreg $end
$var reg 8 g \store[2] [7:0] $end
$upscope $end
$upscope $end
$upscope $end
$scope module cpu_tb $end
$scope module mycpu $end
$scope module myreg $end
$var reg 8 h \store[3] [7:0] $end
$upscope $end
$upscope $end
$upscope $end
$scope module cpu_tb $end
$scope module mycpu $end
$scope module myreg $end
$var reg 8 i \store[4] [7:0] $end
$upscope $end
$upscope $end
$upscope $end
$scope module cpu_tb $end
$scope module mycpu $end
$scope module myreg $end
$var reg 8 j \store[5] [7:0] $end
$upscope $end
$upscope $end
$upscope $end
$scope module cpu_tb $end
$scope module mycpu $end
$scope module myreg $end
$var reg 8 k \store[6] [7:0] $end
$upscope $end
$upscope $end
$upscope $end
$scope module cpu_tb $end
$scope module mycpu $end
$scope module myreg $end
$var reg 8 l \store[7] [7:0] $end
$upscope $end
$upscope $end
$upscope $end
$enddefinitions $end
#0
$dumpvars
bx l
bx k
bx j
bx i
bx h
bx g
bx f
bx e
bx d
bx c
bx b
bx a
bx `
bx _
bx ^
bx ]
bx \
bx [
bx Z
bx Y
bx X
bx W
bx V
bx U
bx T
bx S
bx R
bx Q
bx P
bx O
bx N
bx M
bx L
xK
xJ
xI
xH
bx G
bx F
bx E
bx D
bx C
xB
bx A
bx @
bx ?
x>
bx =
x<
bx ;
bx :
bx 9
bx 8
bx 7
x6
x5
bx 4
bx 3
bx 2
b100000000 1
00
bx /
0.
bx -
bx ,
b1000 +
1*
0)
bx (
bx '
bx &
0%
0$
bx #
0"
bx !
$end
#4
b0 G
1)
#5
b0 l
b0 k
b0 j
b0 i
b0 h
b0 g
b0 f
b0 e
b0 '
b0 @
0*
#6
b100 G
#7
b10000 C
b10000 D
b100 `
b0 b
b101 d
b1000000000000000101 (
b1000000000000000101 3
#8
06
05
b101 F
b101 L
b101 T
b101 V
b101 Y
b101 \
0<
0>
1B
0K
0J
1I
0H
b0 =
b0 M
0)
#9
b101 ?
b101 _
b101 &
b101 -
b101 2
b101 ;
b101 S
b0 !
b0 ,
b0 A
b0 E
b0x0x P
b0x0x Z
bx1x1 N
bx1x1 ]
b101 O
b101 U
b10100 7
b0 9
b0 R
b0 X
b0 [
b0 ^
b0 a
b0 8
b0 c
#10
b101 N
b101 ]
b0 P
b0 Z
b0 :
#11
b101 Q
b101 W
#12
1)
#13
b101 i
b100 '
b100 @
#14
b1000 G
#15
b10100 C
b10100 D
b11 F
b11 L
b11 T
b11 V
b11 Y
b11 \
b101 `
b11 d
b1010000000000000011 (
b1010000000000000011 3
b11000 7
#16
b11 ?
b11 _
b11 &
b11 -
b11 2
b11 ;
b11 S
b11 N
b11 ]
b11 O
b11 U
0)
#17
b11100 7
b11 Q
b11 W
#20
1)
#21
b1000 '
b1000 @
b11 j
#22
b1100 G
#23
b0 C
b0 D
b0 F
b0 L
b0 T
b0 V
b0 Y
b0 \
b0 `
b100 b
b0 d
b1011000000000000010000000000 (
b1011000000000000010000000000 3
b100000 7
#24
b0 ?
b0 _
10
1%
1<
b0 &
b0 -
b0 2
b0 ;
b0 S
b0 N
b0 ]
1"
0B
b0 O
b0 U
0)
#25
b101 !
b101 ,
b101 A
b1100 7
b0 Q
b0 W
b101 9
b101 R
b101 X
b101 [
b101 ^
b101 a
#26
b101 N
b101 ]
#27
b101 Q
b101 W
#28
1)
#32
0)
#36
1)
#40
0)
#44
1)
#48
0)
#52
1)
#56
0)
#60
1)
#64
0)
#68
0"
1)
00
0%
#69
b1100 '
b1100 @
#70
b10000 G
#71
b1 F
b1 L
b1 T
b1 V
b1 Y
b1 \
b101 b
b1 d
b1011000000000000010100000001 (
b1011000000000000010100000001 3
b10000 7
#72
b1 ?
b1 _
10
1%
0<
b1 &
b1 -
b1 2
b1 ;
b1 S
b1 P
b1 Z
1"
b1 O
b1 U
0)
#73
b11 !
b11 ,
b11 A
b110 Q
b110 W
b11 9
b11 R
b11 X
b11 [
b11 ^
b11 a
#74
b11 N
b11 ]
#75
b100 Q
b100 W
#76
1)
#80
0)
#84
1)
#88
0)
#92
1)
#96
0)
#100
1)
#104
0)
#108
1)
#112
0)
#116
0"
1)
00
0%
#117
b10000 '
b10000 @
#118
b10100 G
#119
b10000 C
b10000 D
b101 F
b101 L
b101 T
b101 V
b101 Y
b101 \
b100 `
b100 b
b101 d
b10000001000000010000000101 (
b10000001000000010000000101 3
b10100 7
#120
b100 ?
b100 _
b0 F
b0 L
b0 T
b0 V
b0 Y
b0 \
b100 &
b100 -
b100 2
b100 ;
b100 S
b111 N
b111 ]
1B
0I
b1 =
b1 M
b101 O
b101 U
0)
#121
b11 F
b11 L
b11 T
b11 V
b11 Y
b11 \
b101 !
b101 ,
b101 A
b11 E
b0 P
b0 Z
b11 N
b11 ]
b0 O
b0 U
b100100 7
b101 9
b101 R
b101 X
b101 [
b101 ^
b101 a
b11 8
b11 c
#122
b1 P
b1 Z
b11 O
b11 U
b111 N
b111 ]
b11111101 :
#123
b1000 ?
b1000 _
b1000 &
b1000 -
b1000 2
b1000 ;
b1000 S
b1000 Q
b1000 W
#124
1)
#125
b1000 i
b10100 '
b10100 @
#126
b11000 G
#127
b10100 C
b10100 D
b101 `
b1000 !
b1000 ,
b1000 A
b11000001010000010000000101 (
b11000001010000010000000101 3
b1000 9
b1000 R
b1000 X
b1000 [
b1000 ^
b1000 a
b101000 7
#128
b11111101 F
b11111101 L
b11111101 T
b11111101 V
b11111101 Y
b11111101 \
b11111101 E
1H
b1011 N
b1011 ]
b0 P
b0 Z
0)
#129
b1000 P
b1000 Z
b11111101 N
b11111101 ]
b11111101 O
b11111101 U
b101100 7
#130
b101 ?
b101 _
b101 &
b101 -
b101 2
b101 ;
b101 S
b101 Q
b101 W
#132
1)
#133
b11000 '
b11000 @
b101 j
#134
b11100 G
#135
b11000 C
b11000 D
b110 `
b0 b
b0 d
b1001000001100000000000000000 (
b1001000001100000000000000000 3
b110000 7
b101 8
b101 c
#136
1.
1%
bx ?
bx _
b0 F
b0 L
b0 T
b0 V
b0 Y
b0 \
b11111101 &
b11111101 -
b11111101 2
b11111101 ;
b11111101 S
b101 E
1$
1>
1I
0H
b0 =
b0 M
b11111011 :
0)
#137
1<
b0 &
b0 -
b0 2
b0 ;
b0 S
b0 !
b0 ,
b0 A
b0 E
b0 P
b0 Z
b1000 N
b1000 ]
b0 O
b0 U
b110100 7
b0 9
b0 R
b0 X
b0 [
b0 ^
b0 a
b0 8
b0 c
#138
b0 N
b0 ]
b0 :
#139
b0 Q
b0 W
#140
1)
#144
0)
#148
1)
#152
0)
#156
1)
#160
0)
#164
1)
#168
0)
#172
1)
#176
0)
#180
0$
b101 ?
b101 _
1)
0.
0%
b101 #
b101 /
b101 4
#181
b11100 '
b11100 @
b101 k
#182
b100000 G
#183
b11100 C
b11100 D
b1 F
b1 L
b1 T
b1 V
b1 Y
b1 \
b111 `
b1 d
b1001000001110000000000000001 (
b1001000001110000000000000001 3
b111000 7
#184
1.
1%
0<
b1 &
b1 -
b1 2
b1 ;
b1 S
b1 N
b1 ]
1$
b1 O
b1 U
0)
#185
b111100 7
b1 Q
b1 W
#188
1)
#192
0)
#196
1)
#200
0)
#204
1)
#208
0)
#212
1)
#216
0)
#220
1)
#224
0)
#228
0$
b11 ?
b11 _
1)
0.
0%
b11 #
b11 /
b11 4
#229
b100000 '
b100000 @
b11 l
#230
b100100 G
#231
bx00 C
bx00 D
bx F
bx L
bx T
bx V
bx Y
bx \
bx `
bx b
bx d
bx (
bx 3
b1000000 7
#232
bx &
bx -
bx 2
bx ;
bx S
bx N
bx ]
bx O
bx U
0)
#233
bx !
bx ,
bx A
bx E
bx 7
bx Q
bx W
bx 9
bx R
bx X
bx [
bx ^
bx a
bx 8
bx c
#234
bx P
bx Z
bx :
#236
1)
#237
b100100 '
b100100 @
#238
b101000 G
#240
0)
#244
1)
#245
b101000 '
b101000 @
#246
b101100 G
#248
0)
#252
1)
#253
b101100 '
b101100 @
#254
b110000 G
#256
0)
#260
1)
#261
b110000 '
b110000 @
#262
b110100 G
#264
0)
#268
1)
#269
b110100 '
b110100 @
#270
b111000 G
#272
0)
#276
1)
#277
b111000 '
b111000 @
#278
b111100 G
#280
0)
#284
1)
#285
b111100 '
b111100 @
#286
b1000000 G
#288
0)
#292
1)
#293
b1000000 '
b1000000 @
#294
b1000100 G
#296
0)
#300
1)
#301
b1000100 '
b1000100 @
#302
b1001000 G
#304
0)
#308
1)
#309
b1001000 '
b1001000 @
#310
b1001100 G
#312
0)
#316
1)
#317
b1001100 '
b1001100 @
#318
b1010000 G
#320
0)
#324
1)
#325
b1010000 '
b1010000 @
#326
b1010100 G
#328
0)
#332
1)
#333
b1010100 '
b1010100 @
#334
b1011000 G
#336
0)
#340
1)
#341
b1011000 '
b1011000 @
#342
b1011100 G
#344
0)
#348
1)
#349
b1011100 '
b1011100 @
#350
b1100000 G
#352
0)
#356
1)
#357
b1100000 '
b1100000 @
#358
b1100100 G
#360
0)
#364
1)
#365
b1100100 '
b1100100 @
#366
b1101000 G
#368
0)
#372
1)
#373
b1101000 '
b1101000 @
#374
b1101100 G
#376
0)
#380
1)
#381
b1101100 '
b1101100 @
#382
b1110000 G
#384
0)
#388
1)
#389
b1110000 '
b1110000 @
#390
b1110100 G
#392
0)
#396
1)
#397
b1110100 '
b1110100 @
#398
b1111000 G
#400
0)
#404
1)
#405
b1111000 '
b1111000 @
#406
b1111100 G
#408
0)
#412
1)
#413
b1111100 '
b1111100 @
#414
b10000000 G
#416
0)
#420
1)
#421
b10000000 '
b10000000 @
#422
b10000100 G
#424
0)
#428
1)
#429
b10000100 '
b10000100 @
#430
b10001000 G
#432
0)
#436
1)
#437
b10001000 '
b10001000 @
#438
b10001100 G
#440
0)
#444
1)
#445
b10001100 '
b10001100 @
#446
b10010000 G
#448
0)
#452
1)
#453
b10010000 '
b10010000 @
#454
b10010100 G
#456
0)
#460
1)
#461
b10010100 '
b10010100 @
#462
b10011000 G
#464
0)
#468
1)
#469
b10011000 '
b10011000 @
#470
b10011100 G
#472
0)
#476
1)
#477
b10011100 '
b10011100 @
#478
b10100000 G
#480
0)
#484
1)
#485
b10100000 '
b10100000 @
#486
b10100100 G
#488
0)
#492
1)
#493
b10100100 '
b10100100 @
#494
b10101000 G
#496
0)
#500
1)
#501
b10101000 '
b10101000 @
#502
b10101100 G
